djangolg/__init__.py
djangolg/apps.py
djangolg/events.py
djangolg/exceptions.py
djangolg/fields.py
djangolg/forms.py
djangolg/keys.py
djangolg/lg.py
djangolg/local_settings.py.example
djangolg/methods.py
djangolg/models.py
djangolg/settings.py
djangolg/tests.py
djangolg/types.py
djangolg/urls.py
djangolg/views.py
djangolg/dialects/__init__.py
djangolg/dialects/base.py
djangolg/dialects/cisco_ios.py
djangolg/management/__init__.py
djangolg/management/commands/__init__.py
djangolg/management/commands/lg.py
djangolg/methods/__init__.py
djangolg/methods/base.py
djangolg/methods/bgp_as_path.py
djangolg/methods/bgp_community.py
djangolg/methods/bgp_prefix.py
djangolg/methods/ping.py
djangolg/methods/traceroute.py
djangolg/migrations/0001_initial.py
djangolg/migrations/0002_upgrade_0_2_2.py
djangolg/migrations/__init__.py
djangolg/static/djangolg/css/base.css
djangolg/static/djangolg/img/logo.jpg
djangolg/static/djangolg/img/nav.jpg
djangolg/static/djangolg/img/small_logo.jpg
djangolg/static/djangolg/js/lg.js
djangolg/templates/djangolg/base.html
djangolg/templates/djangolg/controls.html
djangolg/templates/djangolg/footer.html
djangolg/templates/djangolg/help.html
djangolg/templates/djangolg/lg.html
djangolg/templates/djangolg/modal.html
djangolg/templates/djangolg/navbar.html
djangolg/templates/djangolg/output.html
djangolg/templates/djangolg/terms.html
djangolg/textfsm/cisco_ios-xe/bgp_prefix_longer.textfsm
djangolg/views/__init__.py
djangolg/views/helpers.py
djangolg/views/index.py
djangolg/views/lg.py
djangolg/views/terms.py
djangolg-0.2.2.dist-info/DESCRIPTION.rst
djangolg-0.2.2.dist-info/METADATA
djangolg-0.2.2.dist-info/RECORD
djangolg-0.2.2.dist-info/WHEEL
djangolg-0.2.2.dist-info/metadata.json
djangolg-0.2.2.dist-info/top_level.txt
test/__init__.py
test/exec.py
test/settings.py
tests/__init__.py
tests/conftest.py
tests/lg.py
tests/models.py
tests/test_app.py
tests/test_dialects.py
tests/test_exceptions.py
tests/test_fields.py
tests/test_keys.py
tests/test_lg.py
tests/test_management.py
tests/test_methods.py
tests/test_models.py
tests/test_types.py
tests/test_views.py
tests/urls.py
