Metadata-Version: 2.0
Name: djangolg
Version: 0.2.2
Summary: A BGP looking glass based on the Django web framework
Home-page: https://github.com/wolcomm/djangolg
Author: Workonline Communications
Author-email: communications@workonkonline.co.za
License: LICENSE
Download-URL: https://github.com/djangolg/0.2.2
Platform: UNKNOWN
Classifier: Development Status :: 4 - Beta
Classifier: Intended Audience :: Developers
Classifier: License :: OSI Approved :: Apache Software License
Classifier: Topic :: Software Development :: Libraries :: Python Modules
Classifier: Topic :: Internet
Requires-Dist: ipaddress (>=1.0.8,<2.0)
Requires-Dist: napalm (>=1.2.0,<2.0)
Requires-Dist: requests (<3.0,>=2.18.4)
